collect/__init__.py
collect/collector.py
read_conf/__init__.py
read_conf/read_configuration.py
response/__init__.py
response/response.py
snmp_collector/__init__.py
snmp_collector/__main__.py
snmp_collector/event_loop.py
utility/__init__.py
utility/utility.py
simple_snmp_collector-1.0.0.dist-info/LICENSE
simple_snmp_collector-1.0.0.dist-info/METADATA
simple_snmp_collector-1.0.0.dist-info/WHEEL
simple_snmp_collector-1.0.0.dist-info/top_level.txt
simple_snmp_collector-1.0.0.dist-info/RECORD
